{"subjects":[{"episodes_info":"","rate":"7.4","cover_x":1080,"title":"夏日友晴天","url":"https:\/\/movie.douban.com\/subject\/35161768\/","playable":false,"cover":"https://img1.doubanio.com\/view\/photo\/s_ratio_poster\/public\/p2675958609.jpg","id":"35161768","cover_y":1542,"is_new":false},{"episodes_info":"","rate":"6.1","cover_x":729,"title":"追忆迷局","url":"https:\/\/movie.douban.com\/subject\/26615748\/","playable":false,"cover":"https://img9.doubanio.com\/view\/photo\/s_ratio_poster\/public\/p2654959196.jpg","id":"26615748","cover_y":1080,"is_new":false},{"episodes_info":"","rate":"7.6","cover_x":658,"title":"英勇赞曲","url":"https:\/\/movie.douban.com\/subject\/34938576\/","playable":false,"cover":"https://img2.doubanio.com\/view\/photo\/s_ratio_poster\/public\/p2579797743.jpg","id":"34938576","cover_y":1000,"is_new":true},{"episodes_info":"","rate":"7.0","cover_x":750,"title":"孤狼之血2","url":"https:\/\/movie.douban.com\/subject\/35311473\/","playable":false,"cover":"https://img9.doubanio.com\/view\/photo\/s_ratio_poster\/public\/p2657020716.jpg","id":"35311473","cover_y":1063,"is_new":true},{"episodes_info":"","rate":"7.8","cover_x":2084,"title":"游戏男孩 电影版","url":"https:\/\/movie.douban.com\/subject\/35496619\/","playable":false,"cover":"https://img9.doubanio.com\/view\/photo\/s_ratio_poster\/public\/p2674294905.jpg","id":"35496619","cover_y":3000,"is_new":true},{"episodes_info":"","rate":"6.6","cover_x":1434,"title":"南巫","url":"https:\/\/movie.douban.com\/subject\/30359340\/","playable":false,"cover":"https://img2.doubanio.com\/view\/photo\/s_ratio_poster\/public\/p2635906761.jpg","id":"30359340","cover_y":2048,"is_new":false},{"episodes_info":"","rate":"6.5","cover_x":1944,"title":"绿衣骑士","url":"https:\/\/movie.douban.com\/subject\/30372022\/","playable":false,"cover":"https://img9.doubanio.com\/view\/photo\/s_ratio_poster\/public\/p2585680894.jpg","id":"30372022","cover_y":2880,"is_new":false},{"episodes_info":"","rate":"8.1","cover_x":2765,"title":"X特遣队：全员集结","url":"https:\/\/movie.douban.com\/subject\/26741632\/","playable":false,"cover":"https://img2.doubanio.com\/view\/photo\/s_ratio_poster\/public\/p2637084112.jpg","id":"26741632","cover_y":4096,"is_new":false},{"episodes_info":"","rate":"8.7","cover_x":1448,"title":"花束般的恋爱","url":"https:\/\/movie.douban.com\/subject\/34874432\/","playable":false,"cover":"https://img9.doubanio.com\/view\/photo\/s_ratio_poster\/public\/p2623936924.jpg","id":"34874432","cover_y":2048,"is_new":false},{"episodes_info":"","rate":"7.9","cover_x":1500,"title":"猎魔人：狼之噩梦","url":"https:\/\/movie.douban.com\/subject\/34955909\/","playable":false,"cover":"https://img1.doubanio.com\/view\/photo\/s_ratio_poster\/public\/p2675863739.jpg","id":"34955909","cover_y":2222,"is_new":false},{"episodes_info":"","rate":"8.6","cover_x":1600,"title":"健听女孩","url":"https:\/\/movie.douban.com\/subject\/35048413\/","playable":false,"cover":"https://img2.doubanio.com\/view\/photo\/s_ratio_poster\/public\/p2665001891.jpg","id":"35048413","cover_y":2400,"is_new":false},{"episodes_info":"","rate":"7.0","cover_x":3484,"title":"安妮特","url":"https:\/\/movie.douban.com\/subject\/26856202\/","playable":false,"cover":"https://img2.doubanio.com\/view\/photo\/s_ratio_poster\/public\/p2654489281.jpg","id":"26856202","cover_y":4724,"is_new":false},{"episodes_info":"","rate":"5.2","cover_x":2000,"title":"混沌行走","url":"https:\/\/movie.douban.com\/subject\/6874475\/","playable":false,"cover":"https://img9.doubanio.com\/view\/photo\/s_ratio_poster\/public\/p2676934276.jpg","id":"6874475","cover_y":3012,"is_new":false},{"episodes_info":"","rate":"9.2","cover_x":1852,"title":"新·福音战士剧场版：终","url":"https:\/\/movie.douban.com\/subject\/10428501\/","playable":false,"cover":"https://img1.doubanio.com\/view\/photo\/s_ratio_poster\/public\/p2629054917.jpg","id":"10428501","cover_y":2621,"is_new":false},{"episodes_info":"","rate":"6.3","cover_x":864,"title":"黑寡妇","url":"https:\/\/movie.douban.com\/subject\/25828589\/","playable":false,"cover":"https://img1.doubanio.com\/view\/photo\/s_ratio_poster\/public\/p2665872718.jpg","id":"25828589","cover_y":1280,"is_new":false},{"episodes_info":"","rate":"7.2","cover_x":1876,"title":"白蛇2：青蛇劫起","url":"https:\/\/movie.douban.com\/subject\/30435124\/","playable":false,"cover":"https://img2.doubanio.com\/view\/photo\/s_ratio_poster\/public\/p2676545572.jpg","id":"30435124","cover_y":3000,"is_new":false},{"episodes_info":"","rate":"5.4","cover_x":1560,"title":"西游记之再世妖王","url":"https:\/\/movie.douban.com\/subject\/26818326\/","playable":true,"cover":"https://img2.doubanio.com\/view\/photo\/s_ratio_poster\/public\/p2673991933.jpg","id":"26818326","cover_y":3000,"is_new":false},{"episodes_info":"","rate":"7.1","cover_x":1013,"title":"静水城","url":"https:\/\/movie.douban.com\/subject\/34614665\/","playable":false,"cover":"https://img2.doubanio.com\/view\/photo\/s_ratio_poster\/public\/p2654990612.jpg","id":"34614665","cover_y":1500,"is_new":false},{"episodes_info":"","rate":"8.3","cover_x":1535,"title":"偶然与想象","url":"https:\/\/movie.douban.com\/subject\/35360296\/","playable":false,"cover":"https://img3.doubanio.com\/view\/photo\/s_ratio_poster\/public\/p2633273330.jpg","id":"35360296","cover_y":2126,"is_new":false},{"episodes_info":"","rate":"7.2","cover_x":5781,"title":"哆啦A梦：伴我同行2","url":"https:\/\/movie.douban.com\/subject\/34913671\/","playable":true,"cover":"https://img2.doubanio.com\/view\/photo\/s_ratio_poster\/public\/p2641407963.jpg","id":"34913671","cover_y":8206,"is_new":false},{"episodes_info":"","rate":"7.2","cover_x":960,"title":"硬汉枪神","url":"https:\/\/movie.douban.com\/subject\/35464967\/","playable":true,"cover":"https://img9.doubanio.com\/view\/photo\/s_ratio_poster\/public\/p2673396594.jpg","id":"35464967","cover_y":1440,"is_new":false},{"episodes_info":"","rate":"5.6","cover_x":1500,"title":"门徒","url":"https:\/\/movie.douban.com\/subject\/34881663\/","playable":false,"cover":"https://img9.doubanio.com\/view\/photo\/s_ratio_poster\/public\/p2646661285.jpg","id":"34881663","cover_y":2312,"is_new":true},{"episodes_info":"","rate":"5.3","cover_x":1080,"title":"速度与激情9","url":"https:\/\/movie.douban.com\/subject\/25728006\/","playable":true,"cover":"https://img9.doubanio.com\/view\/photo\/s_ratio_poster\/public\/p2640611704.jpg","id":"25728006","cover_y":1596,"is_new":false},{"episodes_info":"","rate":"6.4","cover_x":3142,"title":"乔西的虎与鱼","url":"https:\/\/movie.douban.com\/subject\/34905764\/","playable":false,"cover":"https://img1.doubanio.com\/view\/photo\/s_ratio_poster\/public\/p2677553878.jpg","id":"34905764","cover_y":4327,"is_new":false},{"episodes_info":"","rate":"8.4","cover_x":1000,"title":"浪客剑心 最终章 追忆篇","url":"https:\/\/movie.douban.com\/subject\/33407124\/","playable":false,"cover":"https://img1.doubanio.com\/view\/photo\/s_ratio_poster\/public\/p2641350668.jpg","id":"33407124","cover_y":1416,"is_new":false},{"episodes_info":"","rate":"8.0","cover_x":851,"title":"鬼灭之刃 剧场版 无限列车篇","url":"https:\/\/movie.douban.com\/subject\/34845781\/","playable":false,"cover":"https://img9.doubanio.com\/view\/photo\/s_ratio_poster\/public\/p2623798236.jpg","id":"34845781","cover_y":1200,"is_new":false},{"episodes_info":"","rate":"6.8","cover_x":1080,"title":"怪奇宅","url":"https:\/\/movie.douban.com\/subject\/35477218\/","playable":false,"cover":"https://img9.doubanio.com\/view\/photo\/s_ratio_poster\/public\/p2654205515.jpg","id":"35477218","cover_y":1539,"is_new":false},{"episodes_info":"","rate":"6.3","cover_x":1700,"title":"谤法：在此矣","url":"https:\/\/movie.douban.com\/subject\/35145064\/","playable":false,"cover":"https://img9.doubanio.com\/view\/photo\/s_ratio_poster\/public\/p2674501696.jpg","id":"35145064","cover_y":2422,"is_new":false},{"episodes_info":"","rate":"6.5","cover_x":1400,"title":"当男人恋爱时","url":"https:\/\/movie.douban.com\/subject\/35198827\/","playable":false,"cover":"https://img2.doubanio.com\/view\/photo\/s_ratio_poster\/public\/p2656407373.jpg","id":"35198827","cover_y":2100,"is_new":false},{"episodes_info":"","rate":"5.5","cover_x":2540,"title":"水怪2：黑木林","url":"https:\/\/movie.douban.com\/subject\/35132915\/","playable":true,"cover":"https://img2.doubanio.com\/view\/photo\/s_ratio_poster\/public\/p2675925721.jpg","id":"35132915","cover_y":4600,"is_new":false},{"episodes_info":"","rate":"6.4","cover_x":1688,"title":"丛林奇航","url":"https:\/\/movie.douban.com\/subject\/3692602\/","playable":false,"cover":"https://img9.doubanio.com\/view\/photo\/s_ratio_poster\/public\/p2652691446.jpg","id":"3692602","cover_y":2500,"is_new":false},{"episodes_info":"","rate":"7.2","cover_x":1535,"title":"智齿","url":"https:\/\/movie.douban.com\/subject\/27124695\/","playable":false,"cover":"https://img1.doubanio.com\/view\/photo\/s_ratio_poster\/public\/p2633677609.jpg","id":"27124695","cover_y":2126,"is_new":false},{"episodes_info":"","rate":"5.4","cover_x":556,"title":"他是我的全部","url":"https:\/\/movie.douban.com\/subject\/26363586\/","playable":false,"cover":"https://img1.doubanio.com\/view\/photo\/s_ratio_poster\/public\/p2675274438.jpg","id":"26363586","cover_y":810,"is_new":true},{"episodes_info":"","rate":"5.9","cover_x":2000,"title":"俑之城","url":"https:\/\/movie.douban.com\/subject\/30336307\/","playable":true,"cover":"https://img1.doubanio.com\/view\/photo\/s_ratio_poster\/public\/p2656628179.jpg","id":"30336307","cover_y":3000,"is_new":false},{"episodes_info":"","rate":"6.0","cover_x":1701,"title":"明日之战","url":"https:\/\/movie.douban.com\/subject\/30459571\/","playable":false,"cover":"https://img1.doubanio.com\/view\/photo\/s_ratio_poster\/public\/p2678875868.jpg","id":"30459571","cover_y":2721,"is_new":false},{"episodes_info":"","rate":"6.7","cover_x":2765,"title":"人之怒","url":"https:\/\/movie.douban.com\/subject\/27046740\/","playable":true,"cover":"https://img2.doubanio.com\/view\/photo\/s_ratio_poster\/public\/p2642842673.jpg","id":"27046740","cover_y":4096,"is_new":false},{"episodes_info":"","rate":"6.3","cover_x":4320,"title":"王牌保镖2","url":"https:\/\/movie.douban.com\/subject\/30216729\/","playable":false,"cover":"https://img9.doubanio.com\/view\/photo\/s_ratio_poster\/public\/p2647131304.jpg","id":"30216729","cover_y":6660,"is_new":false},{"episodes_info":"","rate":"6.9","cover_x":6759,"title":"黑白魔女库伊拉","url":"https:\/\/movie.douban.com\/subject\/26703121\/","playable":true,"cover":"https://img9.doubanio.com\/view\/photo\/s_ratio_poster\/public\/p2653946775.jpg","id":"26703121","cover_y":10160,"is_new":false},{"episodes_info":"","rate":"7.5","cover_x":2000,"title":"革命者","url":"https:\/\/movie.douban.com\/subject\/35288767\/","playable":true,"cover":"https://img3.doubanio.com\/view\/photo\/s_ratio_poster\/public\/p2666303410.jpg","id":"35288767","cover_y":2789,"is_new":false},{"episodes_info":"","rate":"7.7","cover_x":1000,"title":"酒精计划","url":"https:\/\/movie.douban.com\/subject\/30323120\/","playable":true,"cover":"https://img9.doubanio.com\/view\/photo\/s_ratio_poster\/public\/p2628440526.jpg","id":"30323120","cover_y":1481,"is_new":false},{"episodes_info":"","rate":"9.1","cover_x":960,"title":"普吉岛的最后黄昏","url":"https:\/\/movie.douban.com\/subject\/35472124\/","playable":false,"cover":"https://img9.doubanio.com\/view\/photo\/s_ratio_poster\/public\/p2652268085.jpg","id":"35472124","cover_y":1200,"is_new":false},{"episodes_info":"","rate":"6.2","cover_x":1000,"title":"热带往事","url":"https:\/\/movie.douban.com\/subject\/29984000\/","playable":true,"cover":"https://img9.doubanio.com\/view\/photo\/s_ratio_poster\/public\/p2654729576.jpg","id":"29984000","cover_y":1414,"is_new":false},{"episodes_info":"","rate":"7.0","cover_x":1200,"title":"王国：北方的阿信","url":"https:\/\/movie.douban.com\/subject\/35151297\/","playable":false,"cover":"https://img1.doubanio.com\/view\/photo\/s_ratio_poster\/public\/p2669957808.jpg","id":"35151297","cover_y":1777,"is_new":false},{"episodes_info":"","rate":"6.1","cover_x":1500,"title":"厄运假期","url":"https:\/\/movie.douban.com\/subject\/33423672\/","playable":false,"cover":"https://img1.doubanio.com\/view\/photo\/s_ratio_poster\/public\/p2663205329.jpg","id":"33423672","cover_y":2222,"is_new":false},{"episodes_info":"","rate":"8.6","cover_x":560,"title":"兹山鱼谱","url":"https:\/\/movie.douban.com\/subject\/30409439\/","playable":false,"cover":"https://img9.doubanio.com\/view\/photo\/s_ratio_poster\/public\/p2634797286.jpg","id":"30409439","cover_y":802,"is_new":false},{"episodes_info":"","rate":"6.4","cover_x":729,"title":"血色天劫","url":"https:\/\/movie.douban.com\/subject\/27179288\/","playable":false,"cover":"https://img9.doubanio.com\/view\/photo\/s_ratio_poster\/public\/p2665626425.jpg","id":"27179288","cover_y":1080,"is_new":false},{"episodes_info":"","rate":"8.8","cover_x":6611,"title":"心灵奇旅","url":"https:\/\/movie.douban.com\/subject\/24733428\/","playable":true,"cover":"https://img9.doubanio.com\/view\/photo\/s_ratio_poster\/public\/p2626308994.jpg","id":"24733428","cover_y":9435,"is_new":false},{"episodes_info":"","rate":"8.2","cover_x":2700,"title":"无依之地","url":"https:\/\/movie.douban.com\/subject\/30458949\/","playable":false,"cover":"https://img1.doubanio.com\/view\/photo\/s_ratio_poster\/public\/p2630453887.jpg","id":"30458949","cover_y":4000,"is_new":false},{"episodes_info":"","rate":"7.4","cover_x":2024,"title":"浪客剑心 最终章 人诛篇","url":"https:\/\/movie.douban.com\/subject\/30167974\/","playable":false,"cover":"https://img2.doubanio.com\/view\/photo\/s_ratio_poster\/public\/p2627551613.jpg","id":"30167974","cover_y":2866,"is_new":false},{"episodes_info":"","rate":"7.8","cover_x":2000,"title":"小人物","url":"https:\/\/movie.douban.com\/subject\/34865507\/","playable":false,"cover":"https://img1.doubanio.com\/view\/photo\/s_ratio_poster\/public\/p2640615589.jpg","id":"34865507","cover_y":3000,"is_new":false}]}